laybot_ai/__init__.py
laybot_ai/batch.py
laybot_ai/chat.py
laybot_ai/client.py
laybot_ai/decoder.py
laybot_ai/doc.py
laybot_ai/embed.py
laybot_ai/exceptions.py
laybot_ai/file.py
laybot_ai/fine_tune.py
laybot_ai/portal.py
laybot_ai/stream.py
laybot_ai/vendor.py
laybot_ai-0.1.1.dist-info/licenses/LICENSE
laybot_ai-0.1.1.dist-info/METADATA
laybot_ai-0.1.1.dist-info/WHEEL
laybot_ai-0.1.1.dist-info/top_level.txt
laybot_ai-0.1.1.dist-info/RECORD
