Metadata-Version: 2.4
Name: laybot-ai
Version: 0.1.1
Summary: LayBot LingTeach AI Python SDK
Author-email: LayBot <support@laybot.cn>
License: Apache-2.0
Project-URL: Homepage, https://ai.laybot.cn
Project-URL: Source, https://github.com/laybot/ai-sdk-python
Requires-Python: >=3.8
License-File: LICENSE
Requires-Dist: requests>=2.31
Dynamic: license-file
